LICENSE
README.md
setup.py
MakeSens/MakeSens.py
MakeSens/__init__.py
MakeSens/__main__.py
MakeSens/data_processing.py
test_APIMakeSens.egg-info/PKG-INFO
test_APIMakeSens.egg-info/SOURCES.txt
test_APIMakeSens.egg-info/dependency_links.txt
test_APIMakeSens.egg-info/entry_points.txt
test_APIMakeSens.egg-info/requires.txt
test_APIMakeSens.egg-info/top_level.txt