Metadata-Version: 2.1
Name: test-APIMakeSens
Version: 1.1.8
Summary: test MakeSense API
Home-page: https://github.com/MakeSens-Data/MakeSensAPI_Python
Author: MakeSens
Author-email: makesens19@gmail.com
License: GNU General Public License v3.0
Classifier: Programming Language :: Python :: 3
Classifier: Programming Language :: Python :: 3.9
License-File: LICENSE
